{
  "indexes": [
    {
      "comment": "Backs LeadService.leads and the All-leads table with no source/status filter — filter by organizationId, order by createdAt. Firestore requires this composite index for the equality + orderBy query.",
      "collectionGroup": "leads",
      "queryScope": "COLLECTION",
      "fields": [
        { "fieldPath": "organizationId", "order": "ASCENDING" },
        { "fieldPath": "createdAt", "order": "DESCENDING" }
      ]
    },
    {
      "comment": "All-leads table filtered by source only (LeadService.fetchLeadsPage): organizationId + source equality, order by createdAt.",
      "collectionGroup": "leads",
      "queryScope": "COLLECTION",
      "fields": [
        { "fieldPath": "organizationId", "order": "ASCENDING" },
        { "fieldPath": "source", "order": "ASCENDING" },
        { "fieldPath": "createdAt", "order": "DESCENDING" }
      ]
    },
    {
      "comment": "All-leads table filtered by status only (LeadService.fetchLeadsPage): organizationId + status equality, order by createdAt.",
      "collectionGroup": "leads",
      "queryScope": "COLLECTION",
      "fields": [
        { "fieldPath": "organizationId", "order": "ASCENDING" },
        { "fieldPath": "status", "order": "ASCENDING" },
        { "fieldPath": "createdAt", "order": "DESCENDING" }
      ]
    },
    {
      "comment": "All-leads table filtered by source AND status (LeadService.fetchLeadsPage): organizationId + source + status equality, order by createdAt.",
      "collectionGroup": "leads",
      "queryScope": "COLLECTION",
      "fields": [
        { "fieldPath": "organizationId", "order": "ASCENDING" },
        { "fieldPath": "source", "order": "ASCENDING" },
        { "fieldPath": "status", "order": "ASCENDING" },
        { "fieldPath": "createdAt", "order": "DESCENDING" }
      ]
    }
  ],
  "fieldOverrides": []
}
